dante/__init__.py
dante/asyncdante.py
dante/base.py
dante/sync.py
dante_db-0.1.1.dist-info/METADATA
dante_db-0.1.1.dist-info/WHEEL
dante_db-0.1.1.dist-info/RECORD
