Metadata-Version: 2.3
Name: dante-db
Version: 0.1.1
Summary: Dante, a document store for Python backed by SQLite
Requires-Python: >=3.9
Requires-Dist: aiosqlite>=0.20.0
Requires-Dist: pydantic>=2.8.2
